odoo9_addon_pos_remove_pos_category-9.0.0.1.0-py2.7-nspkg.pth
odoo_addons/pos_remove_pos_category/__openerp__.py
odoo_addons/pos_remove_pos_category/__init__.py
odoo_addons/pos_remove_pos_category/README.rst
odoo_addons/pos_remove_pos_category/models/module.py
odoo_addons/pos_remove_pos_category/models/product.py
odoo_addons/pos_remove_pos_category/models/__init__.py
odoo_addons/pos_remove_pos_category/i18n/it.po
odoo_addons/pos_remove_pos_category/i18n/fr.po
odoo_addons/pos_remove_pos_category/i18n/pos_remove_pos_category.pot
odoo_addons/pos_remove_pos_category/views/assets.xml
odoo_addons/pos_remove_pos_category/views/pos_category_view.xml
odoo_addons/pos_remove_pos_category/views/pos_view.xml
odoo_addons/pos_remove_pos_category/static/src/js/pos_remove_pos_category.js
odoo9_addon_pos_remove_pos_category-9.0.0.1.0.dist-info/top_level.txt
odoo9_addon_pos_remove_pos_category-9.0.0.1.0.dist-info/WHEEL
odoo9_addon_pos_remove_pos_category-9.0.0.1.0.dist-info/RECORD
odoo9_addon_pos_remove_pos_category-9.0.0.1.0.dist-info/metadata.json
odoo9_addon_pos_remove_pos_category-9.0.0.1.0.dist-info/DESCRIPTION.rst
odoo9_addon_pos_remove_pos_category-9.0.0.1.0.dist-info/METADATA
odoo9_addon_pos_remove_pos_category-9.0.0.1.0.dist-info/namespace_packages.txt
