Metadata-Version: 2.0
Name: odoo9-addon-pos-remove-pos-category
Version: 9.0.0.1.0
Summary: POS Remove POS Category
Home-page: https://www.akretion.com
Author: Akretion, Camptocamp SA, Odoo Community Association (OCA)
Author-email: support@odoo-community.org
License: UNKNOWN
Platform: UNKNOWN
Requires-Dist: odoo (<9.1a,>=9.0a)
Classifier: Programming Language :: Python :: 2.7
Classifier: Framework :: Odoo
